Metadata-Version: 1.0
Name: tsoro-distributions
Version: 0.1
Summary: Gaussian distributions
Home-page: UNKNOWN
Author: John Tsoro
Author-email: johntsoroo@gmail.com
License: UNKNOWN
Platform: UNKNOWN
